pytonik_ip_vpn_checker/Version.py
pytonik_ip_vpn_checker/__init__.py
pytonik_ip_vpn_checker/ip.py
pytonik_ip_vpn_checker-1.0.6.dist-info/LICENSE.txt
pytonik_ip_vpn_checker-1.0.6.dist-info/METADATA
pytonik_ip_vpn_checker-1.0.6.dist-info/WHEEL
pytonik_ip_vpn_checker-1.0.6.dist-info/top_level.txt
pytonik_ip_vpn_checker-1.0.6.dist-info/RECORD
